adaendra_immutable_dict/AdaendraImmutableDict.py
adaendra_immutable_dict/__init__.py
adaendra_immutable_dict-1.0.0.dist-info/LICENSE
adaendra_immutable_dict-1.0.0.dist-info/METADATA
adaendra_immutable_dict-1.0.0.dist-info/WHEEL
adaendra_immutable_dict-1.0.0.dist-info/top_level.txt
adaendra_immutable_dict-1.0.0.dist-info/RECORD
