Metadata-Version: 2.1
Name: adaendra-immutable-dict
Version: 1.0.0
Summary: An immutable dict
Home-page: https://github.com/Adaendra/immutable_dict
Author: Maxime G.
License: UNKNOWN
Project-URL: Bug Tracker, https://github.com/Adaendra/immutable_dict/issues
Platform: UNKNOWN
Classifier: Programming Language :: Python :: 3
Classifier: License :: OSI Approved :: GNU General Public License v3 (GPLv3)
Classifier: Operating System :: OS Independent
Requires-Python: >=3.6
License-File: LICENSE
